LICENSE.txt
MANIFEST.in
README.rst
setup.py
SVG42PDF.egg-info/PKG-INFO
SVG42PDF.egg-info/SOURCES.txt
SVG42PDF.egg-info/dependency_links.txt
SVG42PDF.egg-info/entry_points.txt
SVG42PDF.egg-info/requires.txt
SVG42PDF.egg-info/top_level.txt
ext/svg2rlg/setup.py
ext/svg2rlg/svg2rlg.py
ext/svg2rlg/svg2rlg_render_test.py
ext/svg2rlg/test_svg2rlg.py
svg42pdf/__init__.py
svg42pdf/svg2rlg.py
svg42pdf/version.py