Metadata-Version: 1.1
Name: SVG42PDF
Version: 0.2.2
Summary: Program for SVG to PDF conversion.
Home-page: https://github.com/karel-brinda/svg42pdf
Author: Karel Brinda
Author-email: kbrinda@hsph.harvard.edu
License: MIT
Keywords: Graphics,SVG,PDF,Format conversion
Platform: UNKNOWN
Classifier: Development Status :: 5 - Production/Stable
Classifier: Environment :: Console
Classifier: Intended Audience :: Science/Research
Classifier: License :: OSI Approved :: MIT License
Classifier: Natural Language :: English
Classifier: Programming Language :: Python :: 3 :: Only
Classifier: Operating System :: Unix
